[{"id":1,"data":[{"species":"Calanus","rate":751},{"species":"Centropages typicus","rate":82},{"species":"Calanus finmarchicus","rate":64},{"species":"Acartia","rate":53},{"species":"Temora longicornis","rate":50}]},{"id":2,"data":[{"species":"Larus novaehollandiae","rate":365},{"species":"Phalacrocorax melanoleucos","rate":347},{"species":"Phalacrocorax sulcirostris","rate":270},{"species":"Eudyptula minor","rate":17},{"species":"Chelonia mydas","rate":2}]},{"id":3,"data":[{"species":"Trisopterus esmarkii","rate":338},{"species":"Ammodytes marinus","rate":335},{"species":"Alosa pseudoharengus","rate":124},{"species":"Scomber scombrus","rate":105},{"species":"Sprattus sprattus","rate":99}]},{"id":4,"data":[{"species":"Mallotus villosus","rate":950},{"species":"Boreogadus saida","rate":23},{"species":"Neocalanus plumchrus","rate":15},{"species":"Hippoglossoides platessoides","rate":7},{"species":"Sebastes","rate":6}]},{"id":5,"data":[{"species":"Clupea harengus","rate":532},{"species":"Boreogadus saida","rate":215},{"species":"Trisopterus esmarkii","rate":108},{"species":"Sprattus sprattus","rate":81},{"species":"Mallotus villosus","rate":64}]},{"id":6,"data":[{"species":"Pterosperma","rate":777},{"species":"Pterosperma marginatum","rate":63},{"species":"Pterosperma vanhoeffenii","rate":59},{"species":"Calanus","rate":51},{"species":"Pterosperma moebii","rate":50}]},{"id":7,"data":[{"species":"Oithona","rate":565},{"species":"Calanus","rate":141},{"species":"Centropages typicus","rate":133},{"species":"Acartia","rate":93},{"species":"Paracalanus","rate":67}]},{"id":8,"data":[{"species":"Pseudanthias bartlettorum","rate":339},{"species":"Luzonichthys whitleyi","rate":297},{"species":"Lepidozygus tapeinosoma","rate":123},{"species":"Pycnochromis vanderbilti","rate":123},{"species":"Pycnochromis acares","rate":117}]},{"id":9,"data":[{"species":"Pseudocalanus","rate":575},{"species":"Calanus","rate":127},{"species":"Neocalanus plumchrus","rate":123},{"species":"Acartia (Acartiura) longiremis","rate":107},{"species":"Acartia","rate":69}]},{"id":10,"data":[{"species":"Metridia","rate":530},{"species":"Calanus","rate":186},{"species":"Centropages typicus","rate":146},{"species":"Oithona","rate":71},{"species":"Neocalanus plumchrus","rate":68}]},{"id":11,"data":[{"species":"Strongylocentrotus purpuratus","rate":508},{"species":"Pyrosoma atlanticum","rate":163},{"species":"Doryteuthis opalescens","rate":116},{"species":"Mesocentrotus franciscanus","rate":110},{"species":"Sebastes","rate":103}]},{"id":12,"data":[{"species":"Evadne","rate":607},{"species":"Calanus","rate":120},{"species":"Acartia","rate":106},{"species":"Temora longicornis","rate":90},{"species":"Podon","rate":76}]},{"id":13,"data":[{"species":"Acanthogorgia","rate":741},{"species":"Asbestopluma","rate":126},{"species":"Poecillastra","rate":49},{"species":"Dendrophyllia","rate":44},{"species":"Desmophyllum pertusum","rate":41}]},{"id":14,"data":[{"species":"Sebastes","rate":870},{"species":"Mallotus villosus","rate":64},{"species":"Clupea harengus","rate":31},{"species":"Melanogrammus aeglefinus","rate":19},{"species":"Gadus morhua","rate":16}]},{"id":15,"data":[{"species":"Scomber scombrus","rate":930},{"species":"Clupea harengus","rate":53},{"species":"Micromesistius poutassou","rate":11},{"species":"Cyclopterus lumpus","rate":3},{"species":"Maurolicus muelleri","rate":2}]},{"id":16,"data":[{"species":"Dacrygorgia","rate":965},{"species":"Desmophyllum pertusum","rate":19},{"species":"Farrea","rate":13},{"species":"Stylaster","rate":2}]},{"id":17,"data":[{"species":"Mallotus villosus","rate":527},{"species":"Clupea harengus","rate":206},{"species":"Maurolicus muelleri","rate":139},{"species":"Trisopterus esmarkii","rate":67},{"species":"Sprattus sprattus","rate":62}]},{"id":18,"data":[{"species":"Gadus morhua","rate":801},{"species":"Melanogrammus aeglefinus","rate":98},{"species":"Mallotus villosus","rate":48},{"species":"Clupea harengus","rate":38},{"species":"Sebastes","rate":16}]},{"id":19,"data":[{"species":"Desmophyllum pertusum","rate":915},{"species":"Muriceides","rate":35},{"species":"Paramuricea","rate":25},{"species":"Stichopathes","rate":15},{"species":"Stylaster","rate":11}]},{"id":20,"data":[{"species":"Stichopathes","rate":930},{"species":"Paramuricea","rate":26},{"species":"Desmophyllum pertusum","rate":20},{"species":"Enallopsammia rostrata","rate":13},{"species":"Acanthogorgia","rate":11}]},{"id":21,"data":[{"species":"Paramuricea","rate":752},{"species":"Madrepora oculata","rate":107},{"species":"Acanthogorgia","rate":60},{"species":"Primnoa resedaeformis","rate":51},{"species":"Pennatula","rate":29}]},{"id":22,"data":[{"species":"Beryx splendens","rate":702},{"species":"Thouarella","rate":205},{"species":"Madrepora oculata","rate":58},{"species":"Enallopsammia rostrata","rate":20},{"species":"Paramuricea","rate":15}]},{"id":23,"data":[{"species":"Micromesistius poutassou","rate":815},{"species":"Trisopterus esmarkii","rate":70},{"species":"Benthosema glaciale","rate":67},{"species":"Maurolicus muelleri","rate":33},{"species":"Argentina silus","rate":15}]},{"id":24,"data":[{"species":"Mycale (Mycale) loveni","rate":599},{"species":"Sebastolobus","rate":167},{"species":"Callistephanus","rate":115},{"species":"Microstomus pacificus","rate":60},{"species":"Heteropolypus ritteri","rate":59}]},{"id":25,"data":[{"species":"Paragorgia","rate":635},{"species":"Primnoa wingi","rate":241},{"species":"Trissopathes","rate":74},{"species":"Anthomastus","rate":30},{"species":"Narella","rate":19}]},{"id":26,"data":[{"species":"Desmophyllum dianthus","rate":911},{"species":"Solenosmilia variabilis","rate":32},{"species":"Anthomastus","rate":32},{"species":"Acanthogorgia","rate":14},{"species":"Paramuricea","rate":12}]},{"id":27,"data":[{"species":"Anthomastus","rate":664},{"species":"Hemicorallium","rate":181},{"species":"Chrysogorgia","rate":78},{"species":"Narella","rate":42},{"species":"Chonelasma","rate":34}]},{"id":28,"data":[{"species":"Cyclothone microdon","rate":695},{"species":"Lampanyctus macdonaldi","rate":90},{"species":"Cyclothone braueri","rate":86},{"species":"Scopelogadus beanii","rate":78},{"species":"Protomyctophum arcticum","rate":51}]},{"id":29,"data":[{"species":"Chrysogorgia","rate":312},{"species":"Hemicorallium","rate":246},{"species":"Desmophyllum","rate":178},{"species":"Merluccius merluccius","rate":156},{"species":"Ophiocten hastatum","rate":108}]},{"id":30,"data":[{"species":"Electrona antarctica","rate":923},{"species":"Gymnoscopelus braueri","rate":74},{"species":"Cyclothone microdon","rate":3}]},{"id":31,"data":[{"species":"Solenosmilia variabilis","rate":990},{"species":"Ophiocten hastatum","rate":6},{"species":"Ophiomusa lymani","rate":2},{"species":"Chrysogorgia","rate":2},{"species":"Acanella","rate":1}]},{"id":32,"data":[{"species":"Ophiomusa lymani","rate":965},{"species":"Thenea","rate":21},{"species":"Solenosmilia variabilis","rate":7},{"species":"Acanella","rate":7}]},{"id":33,"data":[{"species":"Crypthelia","rate":580},{"species":"Acanthogorgia","rate":188},{"species":"Keratoisis","rate":107},{"species":"Hemicorallium","rate":72},{"species":"Lepidisis","rate":53}]},{"id":34,"data":[{"species":"Asbestopluma","rate":712},{"species":"Caryophyllia","rate":166},{"species":"Swiftia torreyi","rate":76},{"species":"Paragorgia arborea var. pacifica","rate":24},{"species":"Farrea","rate":22}]},{"id":35,"data":[{"species":"Enallopsammia rostrata","rate":979},{"species":"Chrysogorgia","rate":9},{"species":"Bathypathes","rate":4},{"species":"Chrysogorgia geniculata","rate":4},{"species":"Hemicorallium","rate":4}]},{"id":36,"data":[{"species":"Bathypathes","rate":697},{"species":"Stauropathes","rate":117},{"species":"Chrysogorgia","rate":83},{"species":"Hemicorallium","rate":60},{"species":"Parantipathes","rate":44}]},{"id":37,"data":[{"species":"Acantholaimus","rate":449},{"species":"Halalaimus","rate":309},{"species":"Acantholaimus veitkoehlerae","rate":104},{"species":"Acantholaimus maks","rate":80},{"species":"Deontolaimus","rate":58}]},{"id":38,"data":[{"species":"Nematocarcinus sigmoideus","rate":839},{"species":"Ophiosphalma armigerum","rate":97},{"species":"Amphiophiura convexa","rate":65}]},{"id":39,"data":[{"species":"Hyalonema","rate":805},{"species":"Docosaccus","rate":107},{"species":"Abyssopathes","rate":83},{"species":"Bathygorgia","rate":6}]},{"id":40,"data":[{"species":"Monactis","rate":1000}]},{"id":41,"data":[{"species":"Eurythenes","rate":357},{"species":"Paralicella caperesca","rate":261},{"species":"Paralicella tenuipes","rate":217},{"species":"Paralicella","rate":87},{"species":"Abyssorchomene gerulicorbis","rate":78}]},{"id":42,"data":[{"species":"Haploniscus","rate":506},{"species":"Haploniscus hydroniscoides","rate":476},{"species":"Ringiculoides kurilensis","rate":18}]},{"id":43,"data":[{"species":"Benthesicymus","rate":313},{"species":"Enypniastes eximia","rate":207},{"species":"Coryphaenoides","rate":167},{"species":"Peniagone leander","rate":167},{"species":"Grimpoteuthis","rate":146}]},{"id":44,"data":[{"species":"Benthodytes","rate":750},{"species":"Ophiomusium","rate":250}]},{"id":45,"data":[{"species":"Hyalonema (Corynonema)","rate":604},{"species":"Stephanoscyphistoma","rate":334},{"species":"Notoplites","rate":62}]},{"id":46,"data":[{"species":"Amphiophiura convexa","rate":635},{"species":"Axinodon bornianus","rate":132},{"species":"Propeamussium meridionale","rate":96},{"species":"Ophiosphalma armigerum","rate":84},{"species":"Benthodytes","rate":54}]},{"id":47,"data":[{"species":"Abyssoprimnoa gemina","rate":1000}]},{"id":48,"data":[{"species":"Orchomene","rate":828},{"species":"Paralicella","rate":172},{"species":"Eurythenes","rate":1}]}]